odoo/addons/purchase_order_line_stock_available/README.rst
odoo/addons/purchase_order_line_stock_available/__init__.py
odoo/addons/purchase_order_line_stock_available/__manifest__.py
odoo/addons/purchase_order_line_stock_available/i18n/es.po
odoo/addons/purchase_order_line_stock_available/i18n/it.po
odoo/addons/purchase_order_line_stock_available/i18n/pt_BR.po
odoo/addons/purchase_order_line_stock_available/i18n/purchase_order_line_stock_available.pot
odoo/addons/purchase_order_line_stock_available/i18n/sl.po
odoo/addons/purchase_order_line_stock_available/i18n/zh_CN.po
odoo/addons/purchase_order_line_stock_available/models/__init__.py
odoo/addons/purchase_order_line_stock_available/models/purchase.py
odoo/addons/purchase_order_line_stock_available/readme/CONTRIBUTORS.md
odoo/addons/purchase_order_line_stock_available/readme/DESCRIPTION.md
odoo/addons/purchase_order_line_stock_available/readme/USAGE.md
odoo/addons/purchase_order_line_stock_available/static/description/icon.png
odoo/addons/purchase_order_line_stock_available/static/description/index.html
odoo/addons/purchase_order_line_stock_available/tests/__init__.py
odoo/addons/purchase_order_line_stock_available/tests/test_purchase.py
odoo/addons/purchase_order_line_stock_available/views/purchase_view.xml
odoo_addon_purchase_order_line_stock_available-18.0.1.0.0.2.dist-info/METADATA
odoo_addon_purchase_order_line_stock_available-18.0.1.0.0.2.dist-info/WHEEL
odoo_addon_purchase_order_line_stock_available-18.0.1.0.0.2.dist-info/top_level.txt
odoo_addon_purchase_order_line_stock_available-18.0.1.0.0.2.dist-info/RECORD
